{
  "name": "Oolong",
  "colors": {
    "activityBar.background": "#072020",
    "activityBar.border": "#0b3934",
    "activityBar.foreground": "#E3BC8F",
    "activityBarBadge.background": "#E3BC8F",
    "activityBarBadge.foreground": "#0b3934",
    "activityBarTop.foreground": "#E3BC8F",
    "badge.background": "#E3BC8F",
    "badge.foreground": "#0b3934",
    "breadcrumb.focusForeground": "#E3BC8F",
    "breadcrumb.foreground": "#E3BC8F",
    "button.background": "#0b3934",
    "button.border": "#0b3934",
    "button.foreground": "#E3BC8F",
    "button.hoverBackground": "#072020",
    "button.secondaryBackground": "#082B2B",
    "button.separator": "#E3BC8F",
    "checkbox.background": "#072020",
    "checkbox.border": "#0b3934",
    "commandCenter.activeBackground": "#072626",
    "commandCenter.activeBorder": "#0b3934",
    "commandCenter.background": "#072020",
    "commandCenter.border": "#0b3934",
    "commandCenter.inactiveBorder": "#0b3934",
    "debugConsole.errorForeground": "#ff3a3a",
    "debugConsole.infoForeground": "#E3BC8F",
    "debugConsole.sourceForeground": "#A2D5E0",
    "debugConsole.warningForeground": "#ffce3a",
    "debugIcon.breakpointForeground": "#ff3a3a",
    "debugIcon.pauseForeground": "#1e96ff",
    "debugIcon.restartForeground": "#5AC648",
    "debugIcon.stepBackForeground": "#1e96ff",
    "debugIcon.stepIntoForeground": "#1e96ff",
    "debugIcon.stepOutForeground": "#1e96ff",
    "debugIcon.stepOverForeground": "#1e96ff",
    "debugIcon.stopForeground": "#ff3a3a",
    "debugToolBar.background": "#072020",
    "debugView.stateLabelBackground": "#08302C",
    "descriptionForeground": "#E3BC8F99",
    "dropdown.background": "#072020",
    "dropdown.border": "#0b3934",
    "dropdown.foreground": "#E3BC8F",
    "editor.background": "#072626",
    "editor.findMatchHighlightBackground": "#034661d0",
    "editor.findMatchHighlightBorder": "#034661",
    "editor.findRangeHighlightBackground": "#0a3d3873",
    "editor.foreground": "#E3BC8F",
    "editor.hoverHighlightBackground": "#034661d0",
    "editor.lineHighlightBackground": "#0A3D38",
    "editor.rangeHighlightBackground": "#034661d0",
    "editor.selectionBackground": "#0A3D38",
    "editor.selectionHighlightBorder": "#0F5147",
    "editor.wordHighlightBackground": "#03466110",
    "editor.wordHighlightBorder": "#04648B",
    "editor.stackFrameHighlightBackground": "#E3BC8F3e",
    "editorBracketHighlight.foreground1": "#9AE399",
    "editorBracketHighlight.foreground2": "#A2D5E0",
    "editorBracketHighlight.foreground3": "#5FC3A5",
    "editorBracketHighlight.foreground4": "#C095EF",
    "editorCommentsWidget.replyInputBackground": "#072626",
    "editorCursor.foreground": "#E3BC8F",
    "editorError.foreground": "#ff3a3a",
    "editorGroup.border": "#0b3934",
    "editorGroup.dropBackground": "#1050993f",
    "editorGroupHeader.tabsBackground": "#072020",
    "editorGroupHeader.tabsBorder": "#0b3934",
    "editorIndentGuide.background1": "#E3BC8F38",
    "editorInlayHint.foreground": "#E3BC8Fc5",
    "editorLineNumber.activeForeground": "#E3BC8F",
    "editorLineNumber.foreground": "#E3BC8F",
    "editorLink.activeForeground": "#5AC648",
    "editorRuler.foreground": "#E3BC8F6e",
    "editorStickyScrollHover.background": "#0A3D38",
    "editorSuggestWidget.border": "#0b3934",
    "editorSuggestWidget.focusHighlightForeground": "#1e96ff",
    "editorSuggestWidget.highlightForeground": "#1e96ff",
    "editorWidget.background": "#082B2B",
    "editorWidget.border": "#0b3934",
    "editorWidget.foreground": "#E3BC8F",
    "errorForeground": "#ff3a3a",
    "extensionButton.background": "#0b3934",
    "extensionButton.foreground": "#E3BC8F",
    "extensionButton.hoverBackground": "#072020",
    "extensionButton.separator": "#E3BC8F",
    "focusBorder": "#0b3934",
    "foreground": "#E3BC8F",
    "icon.foreground": "#E3BC8F",
    "input.background": "#082B2B",
    "input.border": "#0b3934",
    "input.foreground": "#E3BC8F",
    "keybindingLabel.background": "#0A3D38",
    "keybindingLabel.border": "#0b3934",
    "keybindingLabel.bottomBorder": "#0b3934",
    "keybindingLabel.foreground": "#E3BC8F",
    "list.activeSelectionBackground": "#0A3D38",
    "list.activeSelectionForeground": "#E3BC8F",
    "list.dropBackground": "#1050993f",
    "list.errorForeground": "#ff3a3a",
    "list.hoverBackground": "#0A3D38",
    "list.hoverForeground": "#E3BC8F",
    "list.inactiveSelectionBackground": "#0A3D38",
    "list.inactiveSelectionForeground": "#E3BC8F",
    "menu.background": "#082B2B",
    "menu.foreground": "#E3BC8F",
    "menu.selectionBackground": "#0A3D38",
    "menu.selectionForeground": "#E3BC8F",
    "notifications.background": "#072020",
    "notifications.border": "#0b3934",
    "panel.background": "#072020",
    "panel.border": "#0b3934",
    "panelInput.border": "#0b3934",
    "panelSection.dropBackground": "#1050993f",
    "panelTitle.activeForeground": "#E3BC8F",
    "panelTitle.inactiveForeground": "#E3BC8F",
    "peekView.border": "#0b3934",
    "peekViewEditor.background": "#082B2B",
    "peekViewResult.background": "#072020",
    "peekViewResult.fileForeground": "#E3BC8F",
    "peekViewResult.lineForeground": "#E3BC8F",
    "peekViewResult.matchHighlightBackground": "#0B413C",
    "peekViewResult.selectionBackground": "#0b3934",
    "peekViewResult.selectionForeground": "#E3BC8F",
    "peekViewTitle.background": "#072020",
    "peekViewTitleLabel.foreground": "#E3BC8F",
    "quickInput.background": "#072020",
    "quickInput.foreground": "#E3BC8F",
    "quickInputList.focusBackground": "#0A3D38",
    "quickInputList.focusIconForeground": "#E3BC8F",
    "sash.hoverBorder": "#E3BC8F",
    "scrollbar.shadow": "#0b3934",
    "scrollbarSlider.activeBackground": "#E3BC8FB0",
    "scrollbarSlider.background": "#E3BC8F60",
    "scrollbarSlider.hoverBackground": "#E3BC8F90",
    "settings.focusedRowBorder": "#0b3934",
    "settings.headerBorder": "#E3BC8F",
    "settings.headerForeground": "#E3BC8F",
    "sideBar.background": "#072020",
    "sideBar.border": "#0b3934",
    "sideBar.dropBackground": "#1050993f",
    "sideBar.foreground": "#E3BC8F",
    "sideBarSectionHeader.background": "#072020",
    "sideBarSectionHeader.border": "#0b3934",
    "statusBar.background": "#072020",
    "statusBar.border": "#0b3934",
    "statusBar.debuggingBackground": "#ac1f0d",
    "statusBar.debuggingForeground": "#E3BC8F",
    "statusBar.foreground": "#E3BC8F",
    "statusBar.noFolderBackground": "#072020",
    "tab.activeBorder": "#072626",
    "tab.activeBorderTop": "#E3BC8F",
    "tab.activeForeground": "#E3BC8F",
    "tab.border": "#0b3934",
    "tab.hoverBackground": "#082B2B",
    "tab.inactiveBackground": "#072020",
    "terminal.dropBackground": "#1050993f",
    "terminal.foreground": "#E3BC8F",
    "textLink.activeForeground": "#1e96ff",
    "textLink.foreground": "#1e96ff",
    "titleBar.activeBackground": "#072020",
    "titleBar.activeForeground": "#E3BC8F",
    "titleBar.border": "#0b3934",
    "titleBar.inactiveBackground": "#072020",
    "titleBar.inactiveForeground": "#E3BC8F92",
    // Gitlens specific (do not sort with the rest)
    "gitlens.gutterBackgroundColor": "#07262600", // Making it transparent actually yields better results
    "gitlens.gutterForegroundColor": "#E3BC8F",
    "gitlens.trailingLineForegroundColor": "#9AE399a0"
  },
  "semanticHighlighting": true,
  "semanticTokenColors": {
    "class": {
      "foreground": "#A2D5E0",
      "fontStyle": ""
    },
    "struct": {
      "foreground": "#A2D5E0",
      "fontStyle": ""
    },
    "enum": {
      "foreground": "#A2D5E0",
      "fontStyle": ""
    },
    "enumMember": {
      "foreground": "#A2D5E0",
      "fontStyle": ""
    },
    // Types
    "type": {
      "foreground": "#A2D5E0"
    },
    "typeAlias": {
      "foreground": "#A2D5E0"
    },
    "*.typeHint": {
      "foreground": "#A2D5E0"
    },
    "interface": {
      "foreground": "#A2D5E0"
    },
    // Macro related
    "macro": {
      "foreground": "#C095EF"
    },
    "builtinAttribute": {
      "foreground": "#C095EF"
    },
    "decorator": {
      "foreground": "#C095EF"
    },
    "deriveHelper": {
      "foreground": "#C095EF"
    },
    "attribute": "#C095EF",
    "attributeBracket": "#C095EF",
    // Functions / Methods
    "method": {},
    "function": {},
    "magicFunction": {
      "fontStyle": "italic"
    },
    // Function Parameters
    "parameter": {
      "fontStyle": ""
    },
    "escapeSequence": {
      "foreground": "#C095EF",
      "fontStyle": "bold"
    },
    "keyword": {
      "fontStyle": "",
      "foreground": "#9AE399"
    },
    "namespace": {
      "fontStyle": ""
    },
    "operator": {
      "fontStyle": ""
    },
    "*.controlFlow": {
      "fontStyle": "bold"
    },
    "*.unsafe": {
      "fontStyle": "bold",
      "foreground": "#fe6f6f"
    },
    "*.consuming": {
      "fontStyle": "italic"
    },
    "*.mutable": {
      "fontStyle": "underline"
    },
    // They're usually upper case
    "*.constant": {
      "fontStyle": ""
    },
    "builtinConstant": {
      "fontStyle": ""
    },
    "*.builtin": {
      "fontStyle": ""
    },
    "*.deprecated": {
      "fontStyle": "strikethrough"
    },
    "comment": "#5bc648"
  },
  "tokenColors": [
    {
      "name": "Comments",
      "scope": ["comment", "punctuation.definition.comment"],
      "settings": {
        // "fontStyle": "italic",
        "foreground": "#5AC648"
      }
    },
    {
      "name": "Strings",
      "scope": [
        "string",
        "punctuation.definition.string",
        "string.quoted.single.python"
      ],
      "settings": {
        "foreground": "#5FC3A5",
        "fontStyle": "" // Empty to enforce no style
      }
    },
    {
      "name": "Strings: Escape Sequences",
      "scope": "constant.character.escape",
      "settings": {
        "foreground": "#C095EF",
        "fontStyle": "bold"
      }
    },
    {
      "name": "Constant Literals",
      "scope": ["constant.numeric", "constant.language.json.comments"],
      "settings": {
        "foreground": "#5FC3A5"
      }
    },
    {
      "name": "YAML: True, False, Null",
      "scope": [
        "constant.language.boolean.yaml",
        "constant.language.null.yaml"
      ],
      "settings": {
        "fontStyle": "bold"
      }
    },
    {
      "name": "Fallback: Enum & Enum Member",
      "scope": ["entity.name.type.enum", "variable.other.enummember"],
      "settings": {
        "foreground": "#A2D5E0",
        "fontStyle": ""
      }
    },
    {
      "name": "Fallback: Namespaces",
      "scope": "entity.name.namespace",
      "settings": {
        "fontStyle": ""
      }
    },
    {
      "name": "Fallback: Types",
      "scope": ["entity.name.type", "support.type", "storage.type"],
      "settings": {
        "foreground": "#A2D5E0",
        "fontStyle": ""
      }
    },
    {
      // NOTE: maybe just keyword.control would work
      "name": "Fallback: Control Flow",
      "scope": ["keyword.control"],
      "settings": {
        "fontStyle": "bold"
      }
    },
    {
      "name": "Fallback: Struct",
      "scope": ["storage.type.struct"],
      "settings": {
        "foreground": "#A2D5E0",
        "fontStyle": ""
      }
    },
    {
      "name": "Fallback: Class",
      "scope": ["entity.name.type.class", "support.class"],
      "settings": {
        "foreground": "#A2D5E0",
        "fontStyle": ""
      }
    },
    {
      "name": "Fallback: Interface",
      "scope": ["entity.name.type.interface"],
      "settings": {
        "foreground": "#A2D5E0",
        "fontStyle": ""
      }
    },
    {
      "name": "Fallback: Function",
      "scope": [
        "entity.name.function",
        "support.function",
        "entity.name.function.member"
      ],
      "settings": {
        "fontStyle": ""
      }
    },
    {
      "name": "Fallback: Macro",
      "scope": ["entity.name.function.macro"],
      "settings": {
        "foreground": "#C095EF"
      }
    },
    {
      "name": "Fallback: Variable",
      "scope": [
        "variable.other.readwrite",
        "entity.name.variable",
        "variable.other.constant",
        "support.constant"
      ],
      "settings": {}
    },
    {
      "name": "Fallback: Parameter",
      "scope": ["variable.parameter"],
      "settings": {}
    },
    {
      "name": "Fallback: Property",
      "scope": ["variable.parameter", "variable.other.parameter"],
      "settings": {}
    },
    {
      "name": "Fallback: Event",
      "scope": ["variable.other.event"],
      "settings": {}
    },
    {
      "name": "Fallback: Keywords",
      "scope": [
        "keyword.function",
        "keyword.control",
        "keyword.var",
        "keyword.type",
        "keyword.package",
        "keyword.interface"
      ],
      "settings": {
        "foreground": "#9AE399"
      }
    },
    {
      "name": "Python: Decorators",
      "scope": [
        "punctuation.definition.decorator.python",
        "entity.name.function.decorator.python",
        "meta.function.decorator.python"
      ],
      "settings": {
        "foreground": "#C095EF"
      }
    },
    {
      "name": "Python Keyword: Declarations",
      "scope": [
        "constant.language.python",
        "keyword.control.flow.python",
        "keyword.control.import.python",
        "keyword.operator.logical.python",
        "storage.type.class.python",
        "storage.type.function.async.python",
        "storage.type.function.lambda.python",
        "storage.type.function.python"
      ],
      "settings": {
        "foreground": "#9AE399"
      }
    },
    {
      // Necessary because they'll inherit the decorator color
      "name": "Python: Function Call Parameter",
      "scope": ["variable.parameter.function-call.python"],
      "settings": {
        "foreground": "#E3BC8F",
        "fontStyle": ""
      }
    },
    {
      "name": "TS Keyword",
      "scope": [
        "constant.language.boolean.false.js",
        "constant.language.boolean.false.jsx",
        "constant.language.boolean.false.ts",
        "constant.language.boolean.false.tsx",
        "constant.language.boolean.true.js",
        "constant.language.boolean.true.jsx",
        "constant.language.boolean.true.ts",
        "constant.language.boolean.true.tsx",
        "constant.language.null.js",
        "constant.language.null.jsx",
        "constant.language.null.ts",
        "constant.language.null.tsx",
        "constant.language.undefined.js",
        "constant.language.undefined.jsx",
        "constant.language.undefined.ts",
        "constant.language.undefined.tsx",
        "keyword.control.as.js",
        "keyword.control.as.jsx",
        "keyword.control.as.ts",
        "keyword.control.as.tsx",
        "keyword.control.conditional.js",
        "keyword.control.conditional.jsx",
        "keyword.control.conditional.ts",
        "keyword.control.conditional.tsx",
        "keyword.control.export.js",
        "keyword.control.export.jsx",
        "keyword.control.export.ts",
        "keyword.control.export.tsx",
        "keyword.control.flow.js",
        "keyword.control.flow.jsx",
        "keyword.control.flow.ts",
        "keyword.control.flow.tsx",
        "keyword.control.from.js",
        "keyword.control.from.jsx",
        "keyword.control.from.ts",
        "keyword.control.from.tsx",
        "keyword.control.import.js",
        "keyword.control.import.jsx",
        "keyword.control.import.ts",
        "keyword.control.import.tsx",
        "keyword.control.loop.js",
        "keyword.control.loop.jsx",
        "keyword.control.loop.ts",
        "keyword.control.loop.tsx",
        "keyword.control.switch.js",
        "keyword.control.switch.jsx",
        "keyword.control.switch.ts",
        "keyword.control.switch.tsx",
        "keyword.control.trycatch.js",
        "keyword.control.trycatch.jsx",
        "keyword.control.trycatch.ts",
        "keyword.control.trycatch.tsx",
        "keyword.operator.expression.delete.js",
        "keyword.operator.expression.delete.jsx",
        "keyword.operator.expression.delete.ts",
        "keyword.operator.expression.delete.tsx",
        "keyword.operator.expression.in.js",
        "keyword.operator.expression.in.jsx",
        "keyword.operator.expression.in.ts",
        "keyword.operator.expression.in.tsx",
        "keyword.operator.expression.instanceof.js",
        "keyword.operator.expression.instanceof.jsx",
        "keyword.operator.expression.instanceof.ts",
        "keyword.operator.expression.instanceof.tsx",
        "keyword.operator.expression.is.js",
        "keyword.operator.expression.is.jsx",
        "keyword.operator.expression.is.ts",
        "keyword.operator.expression.is.tsx",
        "keyword.operator.expression.of.js",
        "keyword.operator.expression.of.jsx",
        "keyword.operator.expression.of.ts",
        "keyword.operator.expression.of.tsx",
        "keyword.operator.expression.typeof.js",
        "keyword.operator.expression.typeof.jsx",
        "keyword.operator.expression.typeof.ts",
        "keyword.operator.expression.typeof.tsx",
        "keyword.operator.new.js",
        "keyword.operator.new.jsx",
        "keyword.operator.new.ts",
        "keyword.operator.new.tsx",
        "storage.modifier.async.js",
        "storage.modifier.async.jsx",
        "storage.modifier.async.ts",
        "storage.modifier.async.tsx",
        "storage.modifier.js",
        "storage.modifier.jsx",
        "storage.modifier.ts",
        "storage.modifier.tsx",
        "storage.type.class.js",
        "storage.type.class.jsx",
        "storage.type.class.ts",
        "storage.type.class.tsx",
        "storage.type.enum.js",
        "storage.type.enum.jsx",
        "storage.type.enum.ts",
        "storage.type.enum.tsx",
        "storage.type.function.js",
        "storage.type.function.jsx",
        "storage.type.function.ts",
        "storage.type.function.tsx",
        "storage.type.interface.js",
        "storage.type.interface.jsx",
        "storage.type.interface.ts",
        "storage.type.interface.tsx",
        "storage.type.js",
        "storage.type.jsx",
        "storage.type.namespace.js",
        "storage.type.namespace.jsx",
        "storage.type.namespace.ts",
        "storage.type.namespace.tsx",
        "storage.type.ts",
        "storage.type.tsx",
        "storage.type.type.js",
        "storage.type.type.jsx",
        "storage.type.type.ts",
        "storage.type.type.tsx",
        "variable.language.super.js",
        "variable.language.super.jsx",
        "variable.language.super.ts",
        "variable.language.super.tsx",
        "variable.language.this.js",
        "variable.language.this.jsx",
        "variable.language.this.ts",
        "variable.language.this.tsx"
      ],
      "settings": {
        "foreground": "#9AE399"
      }
    },
    {
      "name": "JS & TS (X): This",
      "scope": [
        "variable.language.this.js",
        "variable.language.this.jsx",
        "variable.language.this.ts",
        "variable.language.this.tsx"
      ],
      "settings": {
        "fontStyle": "underline"
      }
    },
    {
      "name": "JS & TS (X): Super",
      "scope": [
        "variable.language.super.js",
        "variable.language.super.jsx",
        "variable.language.super.ts",
        "variable.language.super.tsx"
      ],
      "settings": {
        "fontStyle": "underline"
      }
    },
    {
      "name": "Go: Control Flow",
      "scope": ["keyword.control.go"],
      "settings": {
        "fontStyle": "bold"
      }
    },
    {
      "name": "Markup: Headings",
      "scope": ["markup.heading"],
      "settings": {
        "fontStyle": "bold",
        "foreground": "#9AE399"
      }
    },
    {
      "name": "Markup: Code",
      "scope": ["markup.fenced_code.block"],
      "settings": {
        "foreground": "#A2D5E0"
      }
    },
    {
      "name": "Markup: Links",
      "scope": ["markup.underline.link"],
      "settings": {
        "foreground": "#1e96ff"
      }
    },
    {
      "name": "Markup: Italic",
      "scope": ["markup.italic"],
      "settings": {
        "fontStyle": "italic"
      }
    },
    {
      "name": "Markup: Bold",
      "scope": ["markup.bold"],
      "settings": {
        "fontStyle": "bold"
      }
    },
    {
      "name": "Markup: Strikethrough",
      "scope": ["markup.strikethrough"],
      "settings": {
        "fontStyle": "strikethrough"
      }
    },
    {
      "name": "Markup: Underline",
      "scope": ["markup.underline"],
      "settings": {
        "fontStyle": "underline"
      }
    },
    {
      "name": "Markup: Quotes",
      "scope": ["markup.quote"],
      "settings": {
        "foreground": "#5FC3A5",
        "fontStyle": "italic"
      }
    }
  ]
}
